napari_vedo_bridge/__init__.py
napari_vedo_bridge/_cutter_widget.py
napari_vedo_bridge/_mesh.py
napari_vedo_bridge/_points.py
napari_vedo_bridge/_reader.py
napari_vedo_bridge/_sample_data.py
napari_vedo_bridge/_version.py
napari_vedo_bridge/_writer.py
napari_vedo_bridge/napari.yaml
napari_vedo_bridge/utils.py
napari_vedo_bridge/vedo_extension.ui
napari_vedo_bridge/_tests/__init__.py
napari_vedo_bridge/_tests/test_mesh.py
napari_vedo_bridge/_tests/test_points.py
napari_vedo_bridge/_tests/test_reader_and_writer.py
napari_vedo_bridge/_tests/test_sample_data.py
napari_vedo_bridge/_tests/test_widget.py
napari_vedo_bridge/_widgets/__init__.py
napari_vedo_bridge/_widgets/base_widget.py
napari_vedo_bridge/_widgets/base_widget.ui
napari_vedo_bridge-0.3.0.dist-info/licenses/LICENSE
napari_vedo_bridge-0.3.0.dist-info/METADATA
napari_vedo_bridge-0.3.0.dist-info/WHEEL
napari_vedo_bridge-0.3.0.dist-info/entry_points.txt
napari_vedo_bridge-0.3.0.dist-info/top_level.txt
napari_vedo_bridge-0.3.0.dist-info/RECORD
