Metadata-Version: 2.4
Name: napari-vedo-bridge
Version: 0.3.0
Summary: Transfer mesh data between napari and vedo for interactive processing
Author: Johannes Soltwedel, Marco Musy
Author-email: johannes_richard.soltwedel@tu-dresden.de
License: 
Project-URL: Bug Tracker, https://github.com/jo-mueller/napari-vedo-bridge/issues
Project-URL: Documentation, https://github.com/jo-mueller/napari-vedo-bridge#README.md
Project-URL: Source Code, https://github.com/jo-mueller/napari-vedo-bridge
Project-URL: User Support, https://github.com/jo-mueller/napari-vedo-bridge/issues
Classifier: Development Status :: 2 - Pre-Alpha
Classifier: Framework :: napari
Classifier: Intended Audience :: Developers
Classifier: License :: OSI Approved :: BSD License
Classifier: Operating System :: OS Independent
Classifier: Programming Language :: Python
Classifier: Programming Language :: Python :: 3
Classifier: Programming Language :: Python :: 3 :: Only
Classifier: Programming Language :: Python :: 3.8
Classifier: Programming Language :: Python :: 3.9
Classifier: Programming Language :: Python :: 3.10
Classifier: Topic :: Scientific/Engineering :: Image Processing
Requires-Python: >=3.9
License-File: LICENSE
Requires-Dist: numpy
Requires-Dist: magicgui
Requires-Dist: qtpy
Requires-Dist: vedo>=2024.5.2
Requires-Dist: napari-timelapse-processor
Requires-Dist: napari
Provides-Extra: testing
Requires-Dist: tox; extra == "testing"
Requires-Dist: pytest; extra == "testing"
Requires-Dist: pytest-cov; extra == "testing"
Requires-Dist: pytest-qt; extra == "testing"
Requires-Dist: napari; extra == "testing"
Requires-Dist: pyqt5; extra == "testing"
Dynamic: license-file
